notebook_ed/__init__.py
notebook_ed/argumentParser.py
notebook_ed/converter.py
notebook_ed/ignoreFIles.py
notebook_ed/test/__init__.py
notebook_ed/test/test_converter.py
notebook_ed-0.1.4.dist-info/LICENSE
notebook_ed-0.1.4.dist-info/METADATA
notebook_ed-0.1.4.dist-info/WHEEL
notebook_ed-0.1.4.dist-info/entry_points.txt
notebook_ed-0.1.4.dist-info/top_level.txt
notebook_ed-0.1.4.dist-info/RECORD
