Metadata-Version: 2.1
Name: notebook-ed
Version: 0.1.4
Summary: A tool to convert .py files to .ipynb
Home-page: https://github.com/w3cdpass/notebook-ed.git
Author: w3cdpass
Author-email: w3cdpass <kupasva663@gmail.com>
License: # License
Project-URL: Homepage, https://github.com/w3cdpass/notebook-ed
Project-URL: Bug Tracker, https://github.com/w3cdpass/notebook-ed/issues
Keywords: python,converter,notebook,jupyter,py2nb,ipynb,automation,development,tools
Classifier: Development Status :: 3 - Alpha
Classifier: Intended Audience :: Developers
Classifier: Programming Language :: Python :: 3
Classifier: Programming Language :: Python :: 3.7
Classifier: Programming Language :: Python :: 3.8
Classifier: Programming Language :: Python :: 3.9
Classifier: Programming Language :: Python :: 3.10
Classifier: Programming Language :: Python :: 3.11
Requires-Python: >=3.6
License-File: LICENSE
Requires-Dist: nbformat
Requires-Dist: colorama
